nf_consumo/__init__.py
nf_consumo/consumo_service.py
nf_consumo/fs_util.py
hnt_nf_consumo_library-0.0.2.dist-info/METADATA
hnt_nf_consumo_library-0.0.2.dist-info/WHEEL
hnt_nf_consumo_library-0.0.2.dist-info/top_level.txt
hnt_nf_consumo_library-0.0.2.dist-info/RECORD
